gaggle/__init__.py
gaggle/global_configs.py
gaggle/arguments/__init__.py
gaggle/arguments/config_args.py
gaggle/arguments/ga_args.py
gaggle/arguments/individual_args.py
gaggle/arguments/outdir_args.py
gaggle/arguments/problem_args.py
gaggle/arguments/sys_args.py
gaggle/base_nns/__init__.py
gaggle/base_nns/dqn.py
gaggle/base_nns/drqn.py
gaggle/base_nns/lenet.py
gaggle/base_nns/resnet.py
gaggle/base_nns/resnet_x.py
gaggle/base_nns/snet.py
gaggle/ga/__init__.py
gaggle/ga/ga.py
gaggle/ga/ga_factory.py
gaggle/ga/simple_ga.py
gaggle/operators/__init__.py
gaggle/operators/crossover/__init__.py
gaggle/operators/crossover/crossover.py
gaggle/operators/crossover/crossover_factory.py
gaggle/operators/crossover/base_crossovers/__init__.py
gaggle/operators/crossover/base_crossovers/k_point_crossover.py
gaggle/operators/crossover/base_crossovers/uniform_crossover.py
gaggle/operators/mutation/__init__.py
gaggle/operators/mutation/mutation.py
gaggle/operators/mutation/mutation_factory.py
gaggle/operators/mutation/base_mutations/__init__.py
gaggle/operators/mutation/base_mutations/normal_mutation.py
gaggle/operators/mutation/base_mutations/uniform_mutation.py
gaggle/operators/selection/__init__.py
gaggle/operators/selection/selection.py
gaggle/operators/selection/selection_factory.py
gaggle/operators/selection/base_selections/__init__.py
gaggle/operators/selection/base_selections/probabilistic_tournament_selection.py
gaggle/operators/selection/base_selections/relative_weighted_selection.py
gaggle/operators/selection/base_selections/simple_tournament_selection.py
gaggle/operators/selection/base_selections/truncation_selection.py
gaggle/operators/selection/base_selections/weighted_selection.py
gaggle/population/__init__.py
gaggle/population/individual.py
gaggle/population/individual_factory.py
gaggle/population/population_manager.py
gaggle/population/base_individuals/__init__.py
gaggle/population/base_individuals/nn_individual.py
gaggle/population/base_individuals/numpy_individual.py
torch_gaggle-0.0.2.dist-info/LICENSE
torch_gaggle-0.0.2.dist-info/METADATA
torch_gaggle-0.0.2.dist-info/WHEEL
torch_gaggle-0.0.2.dist-info/top_level.txt
torch_gaggle-0.0.2.dist-info/RECORD
